meinconf/__init__.py
meinconf/_version.py
meinconf/config.py
meinconf/eventful.py
meinconf/flask.py
meinconf/utils.py
meinconf/_flask/__init__.py
meinconf/_flask/config.py
meinconf-0.0.6.dist-info/DESCRIPTION.rst
meinconf-0.0.6.dist-info/METADATA
meinconf-0.0.6.dist-info/RECORD
meinconf-0.0.6.dist-info/WHEEL
meinconf-0.0.6.dist-info/metadata.json
meinconf-0.0.6.dist-info/pbr.json
meinconf-0.0.6.dist-info/top_level.txt
