Metadata-Version: 2.0
Name: meinconf
Version: 0.0.6
Summary: 12 factor configuration for all
Home-page: https://github.com/akatrevorjay/meinconf
Author: Trevor Joynson
Author-email: github@skywww.net
License: GPL
Keywords: 12factor
Requires-Dist: attrs
Requires-Dist: six
Requires-Dist: uninhibited
